Workbook
Name CH: Variables!$H$3
Name D: Variables!$H$6
Name FR: Variables!$H$5
Name GB: Variables!$H$8
Name I3liste: 'I3. Dropdown list'!$I$1
Name IT: Variables!$H$7
Name liste_cantons: Variables!$B$11:$B$15
Name tax10pc: Variables!$B$4
Name tax12pc: Variables!$B$6
Name TVACH: Variables!$H$3
Name US: Variables!$H$4

Sheet Variables
A1: #VALUE!
A2: TAX | B2: 0.08 | K2: Departments
G3: CH | H3: 0.087 | K3: HR
A4: TAX | B4: 0.1 | G4: US | H4: 0.1 | K4: MKG
G5: FR | H5: 0.198 | K5: ADMIN
A6: TAX | B6: 0.12 | G6: D | H6: 0.08 | K6: PROD
G7: IT | H7: 0.09 | K7: FINANCE
A8: TAX | B8: 0.1 | G8: GB | H8: 0.098
B10: Liste cantons
B11: Vaud
B12: Genève
B13: Berne
B14: Zurich
B15: Fribourg

Sheet I1. Réf rel. et abs.
A1: =Variables!$A$1 -> #VALUE! | S1: Ludovic Moreau moreau@artofnet.ch
K4: ESTIMATED SALE PRICE
G5: PRODUCT | H5: Cost | I5: Labor | J5: TOTAL | K5: 0.1 | L5: 0.15 | M5: 0.2 | N5: 0.25 | O5: 0.3 | P5: 0.35 | Q5: 0.4
G6: PRODUIT1 | H6: 600 | I6: 200
G7: PRODUIT2 | H7: 753 | I7: 137
G8: PRODUIT3 | H8: 695 | I8: 231
G9: PRODUIT4 | H9: 742 | I9: 228
G10: PRODUIT5 | H10: 804 | I10: 146
G11: PRODUIT6 | H11: 821 | I11: 152
G12: PRODUIT7 | H12: 617 | I12: 246
G13: PRODUIT8 | H13: 455 | I13: 174
G14: PRODUIT9 | H14: 542 | I14: 193
G15: PRODUIT10 | H15: 649 | I15: 215
G16: PRODUIT11 | H16: 822 | I16: 151
G17: PRODUIT12 | H17: 846 | I17: 124
... G26: PRODUIT21 | H26: 736 | I26: 201
G34: SOLUTION (afficher les lignes ci-dessous)
K35: PRIX DE VENTE ESTIME
G36: PRODUIT | H36: Matières premières | I36: Main d'œuvre | J36: TOTAL | K36: 0.1 | L36: 0.15 | M36: 0.2 | N36: 0.25 | O36: 0.3 | P36: 0.35 | Q36: 0.4
G37: PRODUIT1 | H37: 600 | I37: 200 | J37: =H37+I37 -> 800 | K37: =ROUND($J37*(1+K$5)*(1+TVACH),0) -> 957 | L37: =ROUND($J37*(1+L$5)*(1+TVACH),0) -> 1000 | M37: =ROUND($J37*(1+M$5)*(1+TVACH),0) -> 1044 | N37: =ROUND($J37*(1+N$5)*(1+TVACH),0) -> 1087 | O37: =ROUND($J37*(1+O$5)*(1+TVACH),0) -> 1130 | P37: =ROUND($J37*(1+P$5)*(1+TVACH),0) -> 1174 | Q37: =ROUND($J37*(1+Q$5)*(1+TVACH),0) -> 1217
G38: PRODUIT2 | H38: 753 | I38: 137 | J38: =H38+I38 -> 890 | K38: =ROUND($J38*(1+K$5)*(1+TVACH),0) -> 1064 | L38: =ROUND($J38*(1+L$5)*(1+TVACH),0) -> 1113 | M38: =ROUND($J38*(1+M$5)*(1+TVACH),0) -> 1161 | N38: =ROUND($J38*(1+N$5)*(1+TVACH),0) -> 1209 | O38: =ROUND($J38*(1+O$5)*(1+TVACH),0) -> 1258 | P38: =ROUND($J38*(1+P$5)*(1+TVACH),0) -> 1306 | Q38: =ROUND($J38*(1+Q$5)*(1+TVACH),0) -> 1354
G39: PRODUIT3 | H39: 695 | I39: 231 | J39: =H39+I39 -> 926 | K39: =ROUND($J39*(1+K$5)*(1+TVACH),0) -> 1107 | L39: =ROUND($J39*(1+L$5)*(1+TVACH),0) -> 1158 | M39: =ROUND($J39*(1+M$5)*(1+TVACH),0) -> 1208 | N39: =ROUND($J39*(1+N$5)*(1+TVACH),0) -> 1258 | O39: =ROUND($J39*(1+O$5)*(1+TVACH),0) -> 1309 | P39: =ROUND($J39*(1+P$5)*(1+TVACH),0) -> 1359 | Q39: =ROUND($J39*(1+Q$5)*(1+TVACH),0) -> 1409
G40: PRODUIT4 | H40: 742 | I40: 228 | J40: =H40+I40 -> 970 | K40: =ROUND($J40*(1+K$5)*(1+TVACH),0) -> 1160 | L40: =ROUND($J40*(1+L$5)*(1+TVACH),0) -> 1213 | M40: =ROUND($J40*(1+M$5)*(1+TVACH),0) -> 1265 | N40: =ROUND($J40*(1+N$5)*(1+TVACH),0) -> 1318 | O40: =ROUND($J40*(1+O$5)*(1+TVACH),0) -> 1371 | P40: =ROUND($J40*(1+P$5)*(1+TVACH),0) -> 1423 | Q40: =ROUND($J40*(1+Q$5)*(1+TVACH),0) -> 1476
G41: PRODUIT5 | H41: 804 | I41: 146 | J41: =H41+I41 -> 950 | K41: =ROUND($J41*(1+K$5)*(1+TVACH),0) -> 1136 | L41: =ROUND($J41*(1+L$5)*(1+TVACH),0) -> 1188 | M41: =ROUND($J41*(1+M$5)*(1+TVACH),0) -> 1239 | N41: =ROUND($J41*(1+N$5)*(1+TVACH),0) -> 1291 | O41: =ROUND($J41*(1+O$5)*(1+TVACH),0) -> 1342 | P41: =ROUND($J41*(1+P$5)*(1+TVACH),0) -> 1394 | Q41: =ROUND($J41*(1+Q$5)*(1+TVACH),0) -> 1446
G42: PRODUIT6 | H42: 821 | I42: 152 | J42: =H42+I42 -> 973 | K42: =ROUND($J42*(1+K$5)*(1+TVACH),0) -> 1163 | L42: =ROUND($J42*(1+L$5)*(1+TVACH),0) -> 1216 | M42: =ROUND($J42*(1+M$5)*(1+TVACH),0) -> 1269 | N42: =ROUND($J42*(1+N$5)*(1+TVACH),0) -> 1322 | O42: =ROUND($J42*(1+O$5)*(1+TVACH),0) -> 1375 | P42: =ROUND($J42*(1+P$5)*(1+TVACH),0) -> 1428 | Q42: =ROUND($J42*(1+Q$5)*(1+TVACH),0) -> 1481
G43: PRODUIT7 | H43: 617 | I43: 246 | J43: =H43+I43 -> 863 | K43: =ROUND($J43*(1+K$5)*(1+TVACH),0) -> 1032 | L43: =ROUND($J43*(1+L$5)*(1+TVACH),0) -> 1079 | M43: =ROUND($J43*(1+M$5)*(1+TVACH),0) -> 1126 | N43: =ROUND($J43*(1+N$5)*(1+TVACH),0) -> 1173 | O43: =ROUND($J43*(1+O$5)*(1+TVACH),0) -> 1220 | P43: =ROUND($J43*(1+P$5)*(1+TVACH),0) -> 1266 | Q43: =ROUND($J43*(1+Q$5)*(1+TVACH),0) -> 1313
G44: PRODUIT8 | H44: 455 | I44: 174 | J44: =H44+I44 -> 629 | K44: =ROUND($J44*(1+K$5)*(1+TVACH),0) -> 752 | L44: =ROUND($J44*(1+L$5)*(1+TVACH),0) -> 786 | M44: =ROUND($J44*(1+M$5)*(1+TVACH),0) -> 820 | N44: =ROUND($J44*(1+N$5)*(1+TVACH),0) -> 855 | O44: =ROUND($J44*(1+O$5)*(1+TVACH),0) -> 889 | P44: =ROUND($J44*(1+P$5)*(1+TVACH),0) -> 923 | Q44: =ROUND($J44*(1+Q$5)*(1+TVACH),0) -> 957
G45: PRODUIT9 | H45: 542 | I45: 193 | J45: =H45+I45 -> 735 | K45: =ROUND($J45*(1+K$5)*(1+TVACH),0) -> 879 | L45: =ROUND($J45*(1+L$5)*(1+TVACH),0) -> 919 | M45: =ROUND($J45*(1+M$5)*(1+TVACH),0) -> 959 | N45: =ROUND($J45*(1+N$5)*(1+TVACH),0) -> 999 | O45: =ROUND($J45*(1+O$5)*(1+TVACH),0) -> 1039 | P45: =ROUND($J45*(1+P$5)*(1+TVACH),0) -> 1079 | Q45: =ROUND($J45*(1+Q$5)*(1+TVACH),0) -> 1119
G46: PRODUIT10 | H46: 649 | I46: 215 | J46: =H46+I46 -> 864 | K46: =ROUND($J46*(1+K$5)*(1+TVACH),0) -> 1033 | L46: =ROUND($J46*(1+L$5)*(1+TVACH),0) -> 1080 | M46: =ROUND($J46*(1+M$5)*(1+TVACH),0) -> 1127 | N46: =ROUND($J46*(1+N$5)*(1+TVACH),0) -> 1174 | O46: =ROUND($J46*(1+O$5)*(1+TVACH),0) -> 1221 | P46: =ROUND($J46*(1+P$5)*(1+TVACH),0) -> 1268 | Q46: =ROUND($J46*(1+Q$5)*(1+TVACH),0) -> 1315
G47: PRODUIT11 | H47: 822 | I47: 151 | J47: =H47+I47 -> 973 | K47: =ROUND($J47*(1+K$5)*(1+TVACH),0) -> 1163 | L47: =ROUND($J47*(1+L$5)*(1+TVACH),0) -> 1216 | M47: =ROUND($J47*(1+M$5)*(1+TVACH),0) -> 1269 | N47: =ROUND($J47*(1+N$5)*(1+TVACH),0) -> 1322 | O47: =ROUND($J47*(1+O$5)*(1+TVACH),0) -> 1375 | P47: =ROUND($J47*(1+P$5)*(1+TVACH),0) -> 1428 | Q47: =ROUND($J47*(1+Q$5)*(1+TVACH),0) -> 1481
G48: PRODUIT12 | H48: 846 | I48: 124 | J48: =H48+I48 -> 970 | K48: =ROUND($J48*(1+K$5)*(1+TVACH),0) -> 1160 | L48: =ROUND($J48*(1+L$5)*(1+TVACH),0) -> 1213 | M48: =ROUND($J48*(1+M$5)*(1+TVACH),0) -> 1265 | N48: =ROUND($J48*(1+N$5)*(1+TVACH),0) -> 1318 | O48: =ROUND($J48*(1+O$5)*(1+TVACH),0) -> 1371 | P48: =ROUND($J48*(1+P$5)*(1+TVACH),0) -> 1423 | Q48: =ROUND($J48*(1+Q$5)*(1+TVACH),0) -> 1476
... G57: PRODUIT21 | H57: 736 | I57: 201 | J57: =H57+I57 -> 937 | K57: =ROUND($J57*(1+K$5)*(1+TVACH),0) -> 1120 | L57: =ROUND($J57*(1+L$5)*(1+TVACH),0) -> 1171 | M57: =ROUND($J57*(1+M$5)*(1+TVACH),0) -> 1222 | N57: =ROUND($J57*(1+N$5)*(1+TVACH),0) -> 1273 | O57: =ROUND($J57*(1+O$5)*(1+TVACH),0) -> 1324 | P57: =ROUND($J57*(1+P$5)*(1+TVACH),0) -> 1375 | Q57: =ROUND($J57*(1+Q$5)*(1+TVACH),0) -> 1426

Sheet I2. Cond. Formatting
A1: =Variables!$A$1 -> #VALUE!
G8: Highlight cells according to a user-defined filter
G10: Highlighting against the max, min, and average values of the selected range
G14: Adds color bars to each selected cell. The width of the bar is proportional to the value
G16: Adds color shades to each selected cell. The nuance is proportional to the value.
G18: Ajoute des icônes prédéfinesdans chaque cellule sélectionnée. L'icône affichée dépend de la valeur dans la plage. Adds preset icons to each selected cell. The icon displayed depends on the value in the range.
G21: Managing existing Conditional Formatting Rules

Sheet I2. Cond. Formatting (Ex)
A1: =Variables!$A$1 -> #VALUE!
A5: Store | B5: jan | C5: feb | D5: mar | E5: TOTAL | F5: Rank
A6: Store1 | B6: 100 | C6: 200 | D6: 300 | E6: =SUM(B6:D6) -> 600 | F6: =_xlfn.RANK.EQ(E6,$E$6:$E$26,0) -> 19
A7: Store10 | B7: 190 | C7: 245 | D7: 318 | E7: =SUM(B7:D7) -> 753 | F7: =_xlfn.RANK.EQ(E7,$E$6:$E$26,0) -> 6
A8: Store11 | B8: 200 | C8: 250 | D8: 245 | E8: =SUM(B8:D8) -> 695 | F8: =_xlfn.RANK.EQ(E8,$E$6:$E$26,0) -> 10
A9: Store12 | B9: 210 | C9: 255 | D9: 277 | E9: =SUM(B9:D9) -> 742 | F9: =_xlfn.RANK.EQ(E9,$E$6:$E$26,0) -> 7
A10: Store13 | B10: 220 | C10: 260 | D10: 324 | E10: =SUM(B10:D10) -> 804 | F10: =_xlfn.RANK.EQ(E10,$E$6:$E$26,0) -> 5
A11: Store14 | B11: 230 | C11: 265 | D11: 326 | E11: =SUM(B11:D11) -> 821 | F11: =_xlfn.RANK.EQ(E11,$E$6:$E$26,0) -> 4
A12: Store2 | B12: 110 | C12: 205 | D12: 302 | E12: =SUM(B12:D12) -> 617 | F12: =_xlfn.RANK.EQ(E12,$E$6:$E$26,0) -> 18
A13: Store24 | B13: 155 | C13: 112 | D13: 188 | E13: =SUM(B13:D13) -> 455 | F13: =_xlfn.RANK.EQ(E13,$E$6:$E$26,0) -> 21
A14: Store25 | B14: 165 | C14: 225 | D14: 152 | E14: =SUM(B14:D14) -> 542 | F14: =_xlfn.RANK.EQ(E14,$E$6:$E$26,0) -> 20
A15: Store26 | B15: 190 | C15: 214 | D15: 245 | E15: =SUM(B15:D15) -> 649 | F15: =_xlfn.RANK.EQ(E15,$E$6:$E$26,0) -> 16
A16: Store27 | B16: 210 | C16: 258 | D16: 354 | E16: =SUM(B16:D16) -> 822 | F16: =_xlfn.RANK.EQ(E16,$E$6:$E$26,0) -> 3
A17: Store28 | B17: 224 | C17: 301 | D17: 321 | E17: =SUM(B17:D17) -> 846 | F17: =_xlfn.RANK.EQ(E17,$E$6:$E$26,0) -> 2
... A26: Store9 | B26: 180 | C26: 240 | D26: 316 | E26: =SUM(B26:D26) -> 736 | F26: =_xlfn.RANK.EQ(E26,$E$6:$E$26,0) -> 8
B29: ⚫ | C29: Win + . (emoji)
B30: — | C30: Win + . (emoji)
B31: | | C31: MAJ + 7

Sheet I2. Cond. Formatting (Sol.)
A1: =Variables!$A$1 -> #VALUE!
H4: Scaling factor | I4: 20
A5: Store | B5: jan | C5: feb | D5: mar | E5: TOTAL | F5: Rank
A6: Store1 | B6: 100 | C6: 200 | D6: 300 | E6: =SUM(B6:D6) -> 600 | F6: =_xlfn.RANK.EQ(E6,$E$6:$E$26,0) -> 19 | H6: ="|"&REPT("—",E6/$I$4)&"⚫" -> |——————————————————————————————⚫ | R6: ="|"&REPT("—",E6/$I$4)&"⚫" -> |——————————————————————————————⚫
A7: Store10 | B7: 190 | C7: 245 | D7: 318 | E7: =SUM(B7:D7) -> 753 | F7: =_xlfn.RANK.EQ(E7,$E$6:$E$26,0) -> 6 | H7: ="|"&REPT("—",E7/$I$4)&"⚫" -> |—————————————————————————————————————⚫
A8: Store11 | B8: 200 | C8: 250 | D8: 245 | E8: =SUM(B8:D8) -> 695 | F8: =_xlfn.RANK.EQ(E8,$E$6:$E$26,0) -> 10 | H8: ="|"&REPT("—",E8/$I$4)&"⚫" -> |——————————————————————————————————⚫
A9: Store12 | B9: 210 | C9: 255 | D9: 277 | E9: =SUM(B9:D9) -> 742 | F9: =_xlfn.RANK.EQ(E9,$E$6:$E$26,0) -> 7 | H9: ="|"&REPT("—",E9/$I$4)&"⚫" -> |—————————————————————————————————————⚫
A10: Store13 | B10: 220 | C10: 260 | D10: 324 | E10: =SUM(B10:D10) -> 804 | F10: =_xlfn.RANK.EQ(E10,$E$6:$E$26,0) -> 5 | H10: ="|"&REPT("—",E10/$I$4)&"⚫" -> |————————————————————————————————————————⚫
A11: Store14 | B11: 230 | C11: 265 | D11: 326 | E11: =SUM(B11:D11) -> 821 | F11: =_xlfn.RANK.EQ(E11,$E$6:$E$26,0) -> 4 | H11: ="|"&REPT("—",E11/$I$4)&"⚫" -> |—————————————————————————————————————————⚫
A12: Store2 | B12: 110 | C12: 205 | D12: 302 | E12: =SUM(B12:D12) -> 617 | F12: =_xlfn.RANK.EQ(E12,$E$6:$E$26,0) -> 18 | H12: ="|"&REPT("—",E12/$I$4)&"⚫" -> |——————————————————————————————⚫
A13: Store24 | B13: 155 | C13: 112 | D13: 188 | E13: =SUM(B13:D13) -> 455 | F13: =_xlfn.RANK.EQ(E13,$E$6:$E$26,0) -> 21 | H13: ="|"&REPT("—",E13/$I$4)&"⚫" -> |——————————————————————⚫
A14: Store25 | B14: 165 | C14: 225 | D14: 152 | E14: =SUM(B14:D14) -> 542 | F14: =_xlfn.RANK.EQ(E14,$E$6:$E$26,0) -> 20 | H14: ="|"&REPT("—",E14/$I$4)&"⚫" -> |———————————————————————————⚫
A15: Store26 | B15: 190 | C15: 214 | D15: 245 | E15: =SUM(B15:D15) -> 649 | F15: =_xlfn.RANK.EQ(E15,$E$6:$E$26,0) -> 16 | H15: ="|"&REPT("—",E15/$I$4)&"⚫" -> |————————————————————————————————⚫
A16: Store27 | B16: 210 | C16: 258 | D16: 354 | E16: =SUM(B16:D16) -> 822 | F16: =_xlfn.RANK.EQ(E16,$E$6:$E$26,0) -> 3 | H16: ="|"&REPT("—",E16/$I$4)&"⚫" -> |—————————————————————————————————————————⚫
A17: Store28 | B17: 224 | C17: 301 | D17: 321 | E17: =SUM(B17:D17) -> 846 | F17: =_xlfn.RANK.EQ(E17,$E$6:$E$26,0) -> 2 | H17: ="|"&REPT("—",E17/$I$4)&"⚫" -> |——————————————————————————————————————————⚫
A18: Store29 | B18: 290 | C18: 340 | D18: 365 | E18: =SUM(B18:D18) -> 995 | F18: =_xlfn.RANK.EQ(E18,$E$6:$E$26,0) -> 1 | H18: ="|"&REPT("—",E18/$I$4)&"⚫" -> |—————————————————————————————————————————————————⚫
... A26: Store9 | B26: 180 | C26: 240 | D26: 316 | E26: =SUM(B26:D26) -> 736 | F26: =_xlfn.RANK.EQ(E26,$E$6:$E$26,0) -> 8 | H26: ="|"&REPT("—",E26/$I$4)&"⚫" -> |————————————————————————————————————⚫
D28: Max Total | E28: =MAX($E$6:$E$26) -> 995
D29: Max Rank | E29: =MAX($F$6:$F$26) -> 21 | H29: ⚫ | I29: Win + . (emoji)
H30: — | I30: Win + . (emoji)
H31: | | I31: MAJ + 7

Sheet I3. Data Validation
A1: =Variables!$A$1 -> #VALUE!
N4: NB entier
N12: Date
N20: formule
M26: Total max. | N26: 10000
N28: Texte

Sheet I3. Dropdown list
A1: =Variables!$A$1 -> #VALUE!
N4: Text
N11: Cells
N18: Defined name
N25: Formula

Sheet I4. Protection
A1: =Variables!$A$1 -> #VALUE!

Sheet TBL+XLOOKUP
A1: COUNTRY | B1: jan | C1: feb | D1: mar | E1: TOTAL | F1: TOTAL TTC
A2: CH | B2: 100 | C2: 200 | D2: 300 | E2: =SUM(B2:D2) -> 600 | F2: =tbl_xlookup[[#This Row],[TOTAL]]*(1+_xlfn.XLOOKUP(tbl_xlookup[[#This Row],[COUNTRY]],Variables!$G$3:$G$8,Variables!$H$3:$H$8,,0)) -> 652.2
A3: D | B3: 110 | C3: 205 | D3: 302 | E3: =SUM(B3:D3) -> 617 | F3: =tbl_xlookup[[#This Row],[TOTAL]]*(1+_xlfn.XLOOKUP(tbl_xlookup[[#This Row],[COUNTRY]],Variables!$G$3:$G$8,Variables!$H$3:$H$8,,0)) -> 666.36
A4: D | B4: 120 | C4: 210 | D4: 304 | E4: =SUM(B4:D4) -> 634 | F4: =tbl_xlookup[[#This Row],[TOTAL]]*(1+_xlfn.XLOOKUP(tbl_xlookup[[#This Row],[COUNTRY]],Variables!$G$3:$G$8,Variables!$H$3:$H$8,,0)) -> 684.72
A5: CH | B5: 130 | C5: 215 | D5: 306 | E5: =SUM(B5:D5) -> 651 | F5: =tbl_xlookup[[#This Row],[TOTAL]]*(1+_xlfn.XLOOKUP(tbl_xlookup[[#This Row],[COUNTRY]],Variables!$G$3:$G$8,Variables!$H$3:$H$8,,0)) -> 707.637
A6: CH | B6: 140 | C6: 220 | D6: 308 | E6: =SUM(B6:D6) -> 668 | F6: =tbl_xlookup[[#This Row],[TOTAL]]*(1+_xlfn.XLOOKUP(tbl_xlookup[[#This Row],[COUNTRY]],Variables!$G$3:$G$8,Variables!$H$3:$H$8,,0)) -> 726.116
A7: US | B7: 150 | C7: 225 | D7: 310 | E7: =SUM(B7:D7) -> 685 | F7: =tbl_xlookup[[#This Row],[TOTAL]]*(1+_xlfn.XLOOKUP(tbl_xlookup[[#This Row],[COUNTRY]],Variables!$G$3:$G$8,Variables!$H$3:$H$8,,0)) -> 753.5
A8: US | B8: 160 | C8: 230 | D8: 312 | E8: =SUM(B8:D8) -> 702 | F8: =tbl_xlookup[[#This Row],[TOTAL]]*(1+_xlfn.XLOOKUP(tbl_xlookup[[#This Row],[COUNTRY]],Variables!$G$3:$G$8,Variables!$H$3:$H$8,,0)) -> 772.2
A9: GB | B9: 170 | C9: 235 | D9: 314 | E9: =SUM(B9:D9) -> 719 | F9: =tbl_xlookup[[#This Row],[TOTAL]]*(1+_xlfn.XLOOKUP(tbl_xlookup[[#This Row],[COUNTRY]],Variables!$G$3:$G$8,Variables!$H$3:$H$8,,0)) -> 789.462
A10: GB | B10: 180 | C10: 240 | D10: 316 | E10: =SUM(B10:D10) -> 736 | F10: =tbl_xlookup[[#This Row],[TOTAL]]*(1+_xlfn.XLOOKUP(tbl_xlookup[[#This Row],[COUNTRY]],Variables!$G$3:$G$8,Variables!$H$3:$H$8,,0)) -> 808.128
A11: GB | B11: 190 | C11: 245 | D11: 318 | E11: =SUM(B11:D11) -> 753 | F11: =tbl_xlookup[[#This Row],[TOTAL]]*(1+_xlfn.XLOOKUP(tbl_xlookup[[#This Row],[COUNTRY]],Variables!$G$3:$G$8,Variables!$H$3:$H$8,,0)) -> 826.794
A12: CH | B12: 200 | C12: 250 | D12: 320 | E12: =SUM(B12:D12) -> 770 | F12: =tbl_xlookup[[#This Row],[TOTAL]]*(1+_xlfn.XLOOKUP(tbl_xlookup[[#This Row],[COUNTRY]],Variables!$G$3:$G$8,Variables!$H$3:$H$8,,0)) -> 836.99
A13: CH | B13: 210 | C13: 255 | D13: 322 | E13: =SUM(B13:D13) -> 787 | F13: =tbl_xlookup[[#This Row],[TOTAL]]*(1+_xlfn.XLOOKUP(tbl_xlookup[[#This Row],[COUNTRY]],Variables!$G$3:$G$8,Variables!$H$3:$H$8,,0)) -> 855.469
... A24: FR | B24: 190 | C24: 245 | D24: 318 | E24: =SUM(B24:D24) -> 753 | F24: =tbl_xlookup[[#This Row],[TOTAL]]*(1+_xlfn.XLOOKUP(tbl_xlookup[[#This Row],[COUNTRY]],Variables!$G$3:$G$8,Variables!$H$3:$H$8,,0)) -> 902.094
